{
  "game_pk": 776363,
  "game_date": "2025-09-12",
  "home_team": {
    "id": "111",
    "name": "Boston Red Sox",
    "pitcher": {
      "name": "Lucas Giolito",
      "yrfi_allowed": 30.0,
      "yrfi_ratio": "3/10"
    },
    "stats": {
      "base": {
        "value": 33.33333333333333,
        "ratio": "24/72"
      },
      "tendency": {
        "value": 33.33333333333333,
        "ratio": "5/15"
      }
    }
  },
  "away_team": {
    "id": "147",
    "name": "New York Yankees",
    "combined_yrfi_pct": 43.17,
    "pitcher": {
      "name": "Luis Gil",
      "yrfi_allowed": 0.0,
      "yrfi_ratio": "0/3"
    },
    "stats": {
      "base": {
        "value": 40.845070422535215,
        "ratio": "29/71"
      },
      "tendency": {
        "value": 46.666666666666664,
        "ratio": "7/15"
      }
    }
  },
  "prediction": {
    "calculation": {
      "home_team": {
        "base": 33.33333333333333,
        "tendency": 33.33333333333333,
        "combined": 33.33,
        "pitcher_impact": 0.0,
        "adjusted": 23.33
      },
      "away_team": {
        "base": 40.845070422535215,
        "tendency": 46.666666666666664,
        "combined": 43.17,
        "pitcher_impact": 30.0,
        "adjusted": 39.22
      },
      "game_yrfi_probability": 53.4
    },
    "yrfi_probability": 53.4
  },
  "metadata": {
    "generated_at": "2025-09-12T13:19:23.813500",
    "data_source": "season_data.json"
  }
}