{
  "game_pk": 776233,
  "game_date": "2025-09-21",
  "home_team": {
    "id": "119",
    "name": "Los Angeles Dodgers",
    "pitcher": {
      "name": "Tyler Glasnow",
      "yrfi_allowed": 20.0,
      "yrfi_ratio": "2/10"
    },
    "stats": {
      "base": {
        "value": 35.44303797468354,
        "ratio": "28/79"
      },
      "tendency": {
        "value": 13.333333333333334,
        "ratio": "2/15"
      }
    }
  },
  "away_team": {
    "id": "137",
    "name": "San Francisco Giants",
    "combined_yrfi_pct": 36.81,
    "pitcher": {
      "name": "Kai-Wei Teng",
      "yrfi_allowed": 60.0,
      "yrfi_ratio": "3/5"
    },
    "stats": {
      "base": {
        "value": 32.91139240506329,
        "ratio": "26/79"
      },
      "tendency": {
        "value": 40.0,
        "ratio": "6/15"
      }
    }
  },
  "prediction": {
    "calculation": {
      "home_team": {
        "base": 35.44303797468354,
        "tendency": 13.333333333333334,
        "combined": 23.28,
        "pitcher_impact": 60.0,
        "adjusted": 36.13
      },
      "away_team": {
        "base": 32.91139240506329,
        "tendency": 40.0,
        "combined": 36.81,
        "pitcher_impact": 20.0,
        "adjusted": 30.93
      },
      "game_yrfi_probability": 55.88
    },
    "yrfi_probability": 55.88
  },
  "metadata": {
    "generated_at": "2025-09-20T09:36:49.718100",
    "data_source": "season_data.json"
  }
}