{
  "game_pk": 776564,
  "game_date": "2025-08-28",
  "home_team": {
    "id": "110",
    "name": "Baltimore Orioles",
    "pitcher": {
      "name": "Cade Povich",
      "yrfi_allowed": 11.11111111111111,
      "yrfi_ratio": "1/9"
    },
    "stats": {
      "base": {
        "value": 26.865671641791046,
        "ratio": "18/67"
      },
      "tendency": {
        "value": 13.333333333333334,
        "ratio": "2/15"
      }
    }
  },
  "away_team": {
    "id": "111",
    "name": "Boston Red Sox",
    "combined_yrfi_pct": 27.43,
    "pitcher": {
      "name": "Garrett Crochet",
      "yrfi_allowed": 14.285714285714285,
      "yrfi_ratio": "2/14"
    },
    "stats": {
      "base": {
        "value": 27.941176470588236,
        "ratio": "19/68"
      },
      "tendency": {
        "value": 26.666666666666668,
        "ratio": "4/15"
      }
    }
  },
  "prediction": {
    "calculation": {
      "home_team": {
        "base": 26.865671641791046,
        "tendency": 13.333333333333334,
        "combined": 21.45,
        "pitcher_impact": 14.285714285714285,
        "adjusted": 19.3
      },
      "away_team": {
        "base": 27.941176470588236,
        "tendency": 26.666666666666668,
        "combined": 27.43,
        "pitcher_impact": 11.11111111111111,
        "adjusted": 22.54
      },
      "game_yrfi_probability": 37.49
    },
    "yrfi_probability": 37.49
  },
  "metadata": {
    "generated_at": "2025-08-28T13:22:58.885444",
    "data_source": "season_data.json"
  }
}