{
  "game_pk": 823196,
  "game_date": "2026-07-25",
  "home_team": {
    "id": "137",
    "name": "San Francisco Giants",
    "pitcher": {
      "name": "Logan Webb",
      "yrfi_allowed": 0.0,
      "yrfi_ratio": "0/3"
    },
    "stats": {
      "base": {
        "value": 21.27659574468085,
        "ratio": "10/47"
      },
      "tendency": {
        "value": 26.666666666666668,
        "ratio": "4/15"
      }
    }
  },
  "away_team": {
    "id": "108",
    "name": "Los Angeles Angels",
    "combined_yrfi_pct": 28.63,
    "pitcher": {
      "name": "Grayson Rodriguez",
      "yrfi_allowed": 0.0,
      "yrfi_ratio": "0/0"
    },
    "stats": {
      "base": {
        "value": 25.49019607843137,
        "ratio": "13/51"
      },
      "tendency": {
        "value": 33.33333333333333,
        "ratio": "5/15"
      }
    }
  },
  "prediction": {
    "calculation": {
      "home_team": {
        "base": 21.27659574468085,
        "tendency": 26.666666666666668,
        "combined": 23.43,
        "pitcher_impact": 0.0,
        "adjusted": 16.4
      },
      "away_team": {
        "base": 25.49019607843137,
        "tendency": 33.33333333333333,
        "combined": 28.63,
        "pitcher_impact": 0.0,
        "adjusted": 20.04
      },
      "game_yrfi_probability": 33.15
    },
    "yrfi_probability": 33.15
  },
  "metadata": {
    "generated_at": "2026-07-24T15:20:18.759180",
    "data_source": "season_data.json"
  }
}