{
  "game_date": "2025-07-03",
  "home_team": {
    "id": "109",
    "name": "Arizona Diamondbacks",
    "pitcher": {
      "name": "Merrill Kelly",
      "yrfi_allowed": 33.33333333333333,
      "yrfi_ratio": "3/9"
    },
    "stats": {
      "base": {
        "value": 34.883720930232556,
        "ratio": "15/43"
      },
      "tendency": {
        "value": 40.0,
        "ratio": "6/15"
      },
      "adjusted_yrfi_pct": 34.85116279069767
    }
  },
  "away_team": {
    "id": "137",
    "name": "San Francisco Giants",
    "pitcher": {
      "name": "Landen Roupp",
      "yrfi_allowed": 30.0,
      "yrfi_ratio": "3/10"
    },
    "stats": {
      "base": {
        "value": 25.0,
        "ratio": "11/44"
      },
      "tendency": {
        "value": 26.666666666666668,
        "ratio": "4/15"
      },
      "adjusted_yrfi_pct": 27.96666666666666
    }
  },
  "prediction": {
    "base_prob": 31.298449612403108,
    "final_prob": 53.07112093023254,
    "calculation": {
      "formula": "((base × 0.6) + (tendency × 0.4)) × 0.7 + (opponent_pitcher_yrfi × 0.3)",
      "home_team": {
        "base": "34.9% (15/43)",
        "tendency": "40.0% (6/15)",
        "pitcher": "Landen Roupp (0.0% YRFI permitido - 0/1)"
      },
      "away_team": {
        "base": "25.0% (11/44)",
        "tendency": "26.7% (4/15)",
        "pitcher": "Merrill Kelly (0.0% YRFI permitido - 0/1)"
      }
    },
    "text": "# Análisis YRFI - San Francisco Giants @ Arizona Diamondbacks (2025-07-03)\n\n## Información del Partido\n**San Francisco Giants (Visitante) vs Arizona Diamondbacks (Local)**  \n**Lanzadores:** Landen Roupp (@San Francisco Giants) vs Merrill Kelly (@Arizona Diamondbacks)\n\n## Probabilidades YRFI\n\n### Probabilidad YRFI del Partido\n**53.1%** (promedio de ambas probabilidades ajustadas)\n\n### Probabilidad YRFI del Equipo Local\n**34.9%** de que Arizona Diamondbacks anote en la primera entrada\n- Basado en:\n  - Rendimiento de Arizona Diamondbacks como local: 34.9%\n  - Rendimiento del lanzador visitante: 30.0% YRFI permitido\n\n### Probabilidad YRFI del Equipo Visitante\n**28.0%** de que San Francisco Giants anote en la primera entrada\n- Basado en:\n  - Rendimiento de San Francisco Giants como visitante: 25.0%\n  - Rendimiento del lanzador local: 33.3% YRFI permitido\n\n### Cálculo Detallado\n\n#### 1. Probabilidades Base (Temporada Completa)\n- **Arizona Diamondbacks (Local):** 34.9% (15 YRFI en 43 partidos)\n- **San Francisco Giants (Visitante):** 25.0% (11 YRFI en 44 partidos)\n\n#### 2. Cálculo de Tendencias (Últimos 15 partidos)\n- **Arizona Diamondbacks (Local):** 40.0% (6 YRFI en 15 partidos)\n- **San Francisco Giants (Visitante):** 26.7% (4 YRFI en 15 partidos)\n\n#### 3. Combinación con Tendencia (60% base, 40% tendencia)\n- **Arizona Diamondbacks (Local):** (34.9% * 0.6) + (40.0% * 0.4) = **36.9%**\n- **San Francisco Giants (Visitante):** (25.0% * 0.6) + (26.7% * 0.4) = **25.7%**\n\n#### 4. Ajuste por Lanzadores\n*Nota: El rendimiento del lanzador afecta al equipo contrario*\n\n- **Arizona Diamondbacks (Local)**:\n  - Combinado (equipo + tendencia): 36.9%\n  - Afectado por Landen Roupp (visitante): 0.0% YRFI permitido (N/A)\n  - Ajuste (70% equipo + 30% lanzador rival): 25.9%\n\n- **San Francisco Giants (Visitante)**:\n  - Combinado (equipo + tendencia): 25.7%\n  - Afectado por Merrill Kelly (local): 0.0% YRFI permitido (N/A)\n  - Ajuste (70% equipo + 30% lanzador rival): 18.0%\n\n#### 5. Probabilidad Final\n- **Promedio de ajustes:** (25.9% + 18.0%) / 2 = **21.9%**\n\n## Estadísticas Detalladas\n\n\n### Rendimiento de Lanzadores\n- **Merrill Kelly (Arizona Diamondbacks - Local)**:\n  - Rendimiento YRFI: 0.0% (N/A)\n- **Landen Roupp (San Francisco Giants - Visitante)**:\n  - Rendimiento YRFI: 0.0% (N/A)\n### Tendencia (Últimos 15 partidos)\n- **Arizona Diamondbacks:** 40.0% (6/15 partidos)\n- **San Francisco Giants:** 26.7% (4/15 partidos)\n\n### Rendimiento de Lanzadores\n- **Merrill Kelly (Arizona Diamondbacks - Local):**\n  - Total: 33.3% (3/9 aperturas)\n- **Landen Roupp (San Francisco Giants - Visitante):**\n  - Total: 30.0% (3/10 aperturas)\n\n## Resumen de Cálculos\n| Categoría | Arizona Diamondbacks | San Francisco Giants | Promedio |\n|-----------|----------------------|----------------------|----------|\n| **Base** | 34.9% (15/43) | 25.0% (11/44) | 31.3% |\n| **Ajustado** | 34.9% | 28.0% | **53.1%** |\n| **Tendencia** | 40.0% (6/15) | 26.7% (4/15) | - |\n| **Lanzador** | 33.3% (3/9) | 30.0% (3/10) | - |\n\n**Nota:** La probabilidad final del partido (53.1%) es un promedio ponderado que considera tanto el rendimiento histórico de los equipos como el rendimiento específico de los lanzadores en sus respectivos roles (visitante/local)."
  },
  "metadata": {
    "generated_at": "2025-07-02T10:15:55.246772",
    "data_source": "/home/runner/work/mlb-yrfi-predictor/mlb-yrfi-predictor/data/season_data.json"
  }
}