{
  "game_pk": 776174,
  "game_date": "2025-09-26",
  "home_team": {
    "id": "147",
    "name": "New York Yankees",
    "pitcher": {
      "name": "Will Warren",
      "yrfi_allowed": 13.333333333333334,
      "yrfi_ratio": "2/15"
    },
    "stats": {
      "base": {
        "value": 34.61538461538461,
        "ratio": "27/78"
      },
      "tendency": {
        "value": 53.333333333333336,
        "ratio": "8/15"
      }
    }
  },
  "away_team": {
    "id": "110",
    "name": "Baltimore Orioles",
    "combined_yrfi_pct": 26.82,
    "pitcher": {
      "name": "Trevor Rogers",
      "yrfi_allowed": 10.0,
      "yrfi_ratio": "1/10"
    },
    "stats": {
      "base": {
        "value": 26.923076923076923,
        "ratio": "21/78"
      },
      "tendency": {
        "value": 26.666666666666668,
        "ratio": "4/15"
      }
    }
  },
  "prediction": {
    "calculation": {
      "home_team": {
        "base": 34.61538461538461,
        "tendency": 53.333333333333336,
        "combined": 42.1,
        "pitcher_impact": 10.0,
        "adjusted": 32.47
      },
      "away_team": {
        "base": 26.923076923076923,
        "tendency": 26.666666666666668,
        "combined": 26.82,
        "pitcher_impact": 13.333333333333334,
        "adjusted": 22.77
      },
      "game_yrfi_probability": 47.85
    },
    "yrfi_probability": 47.85
  },
  "metadata": {
    "generated_at": "2025-09-26T13:21:28.565293",
    "data_source": "season_data.json"
  }
}