{
  "game_pk": 776558,
  "game_date": "2025-08-28",
  "home_team": {
    "id": "121",
    "name": "New York Mets",
    "pitcher": {
      "name": "Clay Holmes",
      "yrfi_allowed": 23.076923076923077,
      "yrfi_ratio": "3/13"
    },
    "stats": {
      "base": {
        "value": 33.82352941176471,
        "ratio": "23/68"
      },
      "tendency": {
        "value": 20.0,
        "ratio": "3/15"
      }
    }
  },
  "away_team": {
    "id": "146",
    "name": "Miami Marlins",
    "combined_yrfi_pct": 25.44,
    "pitcher": {
      "name": "Por anunciar",
      "yrfi_allowed": 50.0,
      "yrfi_ratio": "0/0"
    },
    "stats": {
      "base": {
        "value": 24.615384615384617,
        "ratio": "16/65"
      },
      "tendency": {
        "value": 26.666666666666668,
        "ratio": "4/15"
      }
    }
  },
  "prediction": {
    "calculation": {
      "home_team": {
        "base": 33.82352941176471,
        "tendency": 20.0,
        "combined": 28.29,
        "pitcher_impact": 50.0,
        "adjusted": 34.81
      },
      "away_team": {
        "base": 24.615384615384617,
        "tendency": 26.666666666666668,
        "combined": 25.44,
        "pitcher_impact": 23.076923076923077,
        "adjusted": 24.73
      },
      "game_yrfi_probability": 50.93
    },
    "yrfi_probability": 50.93
  },
  "metadata": {
    "generated_at": "2025-08-28T13:22:58.938104",
    "data_source": "season_data.json"
  }
}