{
  "game_pk": 776585,
  "game_date": "2025-08-26",
  "home_team": {
    "id": "121",
    "name": "New York Mets",
    "pitcher": {
      "name": "Sean Manaea",
      "yrfi_allowed": 25.0,
      "yrfi_ratio": "1/4"
    },
    "stats": {
      "base": {
        "value": 34.84848484848485,
        "ratio": "23/66"
      },
      "tendency": {
        "value": 33.33333333333333,
        "ratio": "5/15"
      }
    }
  },
  "away_team": {
    "id": "143",
    "name": "Philadelphia Phillies",
    "combined_yrfi_pct": 29.45,
    "pitcher": {
      "name": "Jesús Luzardo",
      "yrfi_allowed": 38.46153846153847,
      "yrfi_ratio": "5/13"
    },
    "stats": {
      "base": {
        "value": 26.865671641791046,
        "ratio": "18/67"
      },
      "tendency": {
        "value": 33.33333333333333,
        "ratio": "5/15"
      }
    }
  },
  "prediction": {
    "calculation": {
      "home_team": {
        "base": 34.84848484848485,
        "tendency": 33.33333333333333,
        "combined": 34.24,
        "pitcher_impact": 38.46153846153847,
        "adjusted": 35.51
      },
      "away_team": {
        "base": 26.865671641791046,
        "tendency": 33.33333333333333,
        "combined": 29.45,
        "pitcher_impact": 25.0,
        "adjusted": 28.12
      },
      "game_yrfi_probability": 53.64
    },
    "yrfi_probability": 53.64
  },
  "metadata": {
    "generated_at": "2025-08-26T13:27:01.231416",
    "data_source": "season_data.json"
  }
}