{
  "game_pk": 824610,
  "game_date": "2026-04-28",
  "home_team": {
    "id": "145",
    "name": "Chicago White Sox",
    "pitcher": {
      "name": "Davis Martin",
      "yrfi_allowed": 0.0,
      "yrfi_ratio": "0/1"
    },
    "stats": {
      "base": {
        "value": 23.076923076923077,
        "ratio": "3/13"
      },
      "tendency": {
        "value": 26.666666666666668,
        "ratio": "4/15"
      }
    }
  },
  "away_team": {
    "id": "108",
    "name": "Los Angeles Angels",
    "combined_yrfi_pct": 36.0,
    "pitcher": {
      "name": "José Soriano",
      "yrfi_allowed": 0.0,
      "yrfi_ratio": "0/3"
    },
    "stats": {
      "base": {
        "value": 33.33333333333333,
        "ratio": "6/18"
      },
      "tendency": {
        "value": 40.0,
        "ratio": "6/15"
      }
    }
  },
  "prediction": {
    "calculation": {
      "home_team": {
        "base": 23.076923076923077,
        "tendency": 26.666666666666668,
        "combined": 24.51,
        "pitcher_impact": 0.0,
        "adjusted": 17.16
      },
      "away_team": {
        "base": 33.33333333333333,
        "tendency": 40.0,
        "combined": 36.0,
        "pitcher_impact": 0.0,
        "adjusted": 25.2
      },
      "game_yrfi_probability": 38.04
    },
    "yrfi_probability": 38.04
  },
  "metadata": {
    "generated_at": "2026-04-28T16:08:14.893126",
    "data_source": "season_data.json"
  }
}