{
  "game_pk": 776592,
  "game_date": "2025-08-26",
  "home_team": {
    "id": "140",
    "name": "Texas Rangers",
    "pitcher": {
      "name": "Jacob deGrom",
      "yrfi_allowed": 33.33333333333333,
      "yrfi_ratio": "4/12"
    },
    "stats": {
      "base": {
        "value": 22.727272727272727,
        "ratio": "15/66"
      },
      "tendency": {
        "value": 33.33333333333333,
        "ratio": "5/15"
      }
    }
  },
  "away_team": {
    "id": "108",
    "name": "Los Angeles Angels",
    "combined_yrfi_pct": 42.27,
    "pitcher": {
      "name": "José Soriano",
      "yrfi_allowed": 33.33333333333333,
      "yrfi_ratio": "4/12"
    },
    "stats": {
      "base": {
        "value": 39.34426229508197,
        "ratio": "24/61"
      },
      "tendency": {
        "value": 46.666666666666664,
        "ratio": "7/15"
      }
    }
  },
  "prediction": {
    "calculation": {
      "home_team": {
        "base": 22.727272727272727,
        "tendency": 33.33333333333333,
        "combined": 26.97,
        "pitcher_impact": 33.33333333333333,
        "adjusted": 28.88
      },
      "away_team": {
        "base": 39.34426229508197,
        "tendency": 46.666666666666664,
        "combined": 42.27,
        "pitcher_impact": 33.33333333333333,
        "adjusted": 39.59
      },
      "game_yrfi_probability": 57.04
    },
    "yrfi_probability": 57.04
  },
  "metadata": {
    "generated_at": "2025-08-25T13:25:31.438700",
    "data_source": "season_data.json"
  }
}