{
  "game_pk": 777014,
  "game_date": "2025-07-25",
  "home_team": {
    "id": "134",
    "name": "Pittsburgh Pirates",
    "pitcher": {
      "name": "Mike Burrows",
      "yrfi_allowed": 33.33333333333333,
      "yrfi_ratio": "2/6"
    },
    "stats": {
      "base": {
        "value": 28.30188679245283,
        "ratio": "15/53"
      },
      "tendency": {
        "value": 6.666666666666667,
        "ratio": "1/15"
      }
    }
  },
  "away_team": {
    "id": "109",
    "name": "Arizona Diamondbacks",
    "combined_yrfi_pct": 31.7,
    "pitcher": {
      "name": "Ryne Nelson",
      "yrfi_allowed": 40.0,
      "yrfi_ratio": "2/5"
    },
    "stats": {
      "base": {
        "value": 30.612244897959183,
        "ratio": "15/49"
      },
      "tendency": {
        "value": 33.33333333333333,
        "ratio": "5/15"
      }
    }
  },
  "prediction": {
    "calculation": {
      "home_team": {
        "base": 28.30188679245283,
        "tendency": 6.666666666666667,
        "combined": 19.65,
        "pitcher_impact": 40.0,
        "adjusted": 25.75
      },
      "away_team": {
        "base": 30.612244897959183,
        "tendency": 33.33333333333333,
        "combined": 31.7,
        "pitcher_impact": 33.33333333333333,
        "adjusted": 32.19
      },
      "game_yrfi_probability": 49.65
    },
    "yrfi_probability": 49.65
  },
  "metadata": {
    "generated_at": "2025-07-25T10:16:23.651166",
    "data_source": "season_data.json"
  }
}